enumerate_iam/__init__.py
enumerate_iam/bruteforce_tests.py
enumerate_iam/generate_bruteforce_tests.py
enumerate_iam/main.py
enumerate_iam/utils/__init__.py
enumerate_iam/utils/json_utils.py
enumerate_iam/utils/remove_metadata.py
amazon_enumerate_iam-1.0.1.dist-info/LICENSE
amazon_enumerate_iam-1.0.1.dist-info/METADATA
amazon_enumerate_iam-1.0.1.dist-info/WHEEL
amazon_enumerate_iam-1.0.1.dist-info/top_level.txt
amazon_enumerate_iam-1.0.1.dist-info/RECORD
