Metadata-Version: 2.1
Name: amazon-enumerate-iam
Version: 1.0.1
Summary: The AWS Enumerate IAM permissions
Home-page: https://github.com/andresriancho/enumerate-iam
Author: andresriancho
License: Apache License 2.0
Platform: any
Classifier: Development Status :: 5 - Production/Stable
Classifier: Intended Audience :: Developers
Classifier: Natural Language :: English
Classifier: License :: OSI Approved :: Apache Software License
Classifier: Programming Language :: Python
Classifier: Programming Language :: Python :: 3
Classifier: Programming Language :: Python :: 3 :: Only
Classifier: Programming Language :: Python :: 3.7
Classifier: Programming Language :: Python :: 3.8
Classifier: Programming Language :: Python :: 3.9
Classifier: Programming Language :: Python :: 3.10
Classifier: Programming Language :: Python :: 3.11
Classifier: Programming Language :: Python :: 3.12
Requires-Python: >= 3.7
License-File: LICENSE
Requires-Dist: botocore (<1.32.0,>=1.31.45)
Requires-Dist: boto3 (>=1.28.45)
